outlier/__init__.py
outlier/outlier.py
outlier_py-0.0.2.dist-info/LICENSE
outlier_py-0.0.2.dist-info/METADATA
outlier_py-0.0.2.dist-info/WHEEL
outlier_py-0.0.2.dist-info/top_level.txt
outlier_py-0.0.2.dist-info/RECORD
